oolongTool/ChangeUser.py
oolongTool/PostMessage.py
oolongTool/SlurmSbath.py
oolongTool/__init__.py
oolongTool/__main__.py
oolongTool/utils/MetricSave.py
oolongTool/utils/SqlSave.py
oolongTool/utils/__init__.py
oolongTool-0.2.94.dist-info/LICENSE
oolongTool-0.2.94.dist-info/METADATA
oolongTool-0.2.94.dist-info/WHEEL
oolongTool-0.2.94.dist-info/entry_points.txt
oolongTool-0.2.94.dist-info/top_level.txt
oolongTool-0.2.94.dist-info/RECORD
